{
  "version": 8,
  "name": "Basic Map",
  "metadata": {},
  "center": [2.187, 41.388],
  "zoom": 15.4,
  "sources": {
    "mapbox-streets": {
      "type": "vector",
      "url": "mapbox://mapbox.mapbox-streets-v8"
    }
  },
  "layers": [
    {
      "id": "background",
      "type": "background",
      "paint": {
        "background-color": "#f3f3f3"
      }
    },
    {
      "id": "water",
      "source": "mapbox-streets",
      "source-layer": "water",
      "type": "fill",
      "paint": {
        "fill-color": "#b4d4e8"
      }
    },
    {
      "id": "roads",
      "source": "mapbox-streets",
      "source-layer": "road",
      "type": "line",
      "paint": {
        "line-color": "#ffffff",
        "line-width": {
          "base": 1.2,
          "stops": [
            [12, 0.5],
            [20, 10]
          ]
        }
      }
    },
    {
      "id": "labels",
      "source": "mapbox-streets",
      "source-layer": "road_label",
      "type": "symbol",
      "layout": {
        "text-field": "{name_en}",
        "text-size": {
          "base": 1.2,
          "stops": [
            [12, 10],
            [20, 16]
          ]
        }
      },
      "paint": {
        "text-color": "#000000"
      }
    },
    {
      "id": "custom-layer",
      "type": "custom",
      "customLayer": "model3d",
      "models": [
        {
          "id": "block",
          "position": [41.388, 2.187, 0],
          "scale": [10, 15, 40],
          "url": "file:///Users/david/dev/mapbox-gl-native/test/fixtures/resources/cube_endavid.json"
        },
        {
          "id": "tree01",
          "position": [41.388966, 2.182626, 0],
          "scale": [10, 10, 10],
          "url": "file:///Users/david/dev/mapbox-gl-native/test/fixtures/resources/tree_endavid.json"
        },
        {
          "id": "tree02",
          "position": [41.389419, 2.183569, 0],
          "scale": [10, 10, 10],
          "url": "file:///Users/david/dev/mapbox-gl-native/test/fixtures/resources/tree_endavid.json"
        }
      ]
    }
  ]
}
